.gitignore
CHANGELOG.md
README.md
allmychanges.cfg.example
setup.py
allmychanges/__init__.py
allmychanges/api.py
allmychanges/client.py
allmychanges/config.py
allmychanges/utils.py
allmychanges.egg-info/PKG-INFO
allmychanges.egg-info/SOURCES.txt
allmychanges.egg-info/dependency_links.txt
allmychanges.egg-info/entry_points.txt
allmychanges.egg-info/requires.txt
allmychanges.egg-info/top_level.txt
examples/__init__.py
examples/subscribe_on_section.py
examples/untrack_all_except_namespace.py