Metadata-Version: 1.0
Name: allmychanges
Version: 0.9.0
Summary: A command line client to AllMyChanges.com.
Home-page: https://github.com/svetlyak40wt/allmychanges
Author: Artemenko Alexander
Author-email: svetlyak.40wt@gmail.com
License: BSD
Keywords: changelog tracker allmychanges release notes
Platform: UNKNOWN
